{
  "HKD": {
    "price": 0.12740476,
    "name": "HKD-USD",
    "lastUpdated": "2025-06-15"
  },
  "CNY": {
    "price": 0.13926607,
    "name": "CNY-USD",
    "lastUpdated": "2025-06-15"
  },
  "0700.HK": {
    "price": 64.97642760000001,
    "originalPrice": 510.0,
    "currency": "HKD",
    "name": "Tencent",
    "lastUpdated": "2025-06-15"
  },
  "TSLA": {
    "price": 325.31,
    "name": "Tesla",
    "lastUpdated": "2025-06-15"
  },
  "VST": {
    "price": 173.75,
    "name": "Vistra Energy",
    "lastUpdated": "2025-06-15"
  },
  "PLTR": {
    "price": 137.4,
    "name": "Palantir",
    "lastUpdated": "2025-06-15"
  },
  "RKLB": {
    "price": 25.41,
    "name": "Rocket Lab",
    "lastUpdated": "2025-06-15"
  },
  "GOOGL": {
    "price": 174.67,
    "name": "Google",
    "lastUpdated": "2025-06-15"
  },
  "VOO": {
    "price": 548.77,
    "name": "Vanguard S&P 500 ETF",
    "lastUpdated": "2025-06-15"
  }
}