{
  "HKD": {
    "price": 0.1281877,
    "name": "HKD-USD",
    "lastUpdated": "2025-09-04"
  },
  "CNY": {
    "price": 0.14003837,
    "name": "CNY-USD",
    "lastUpdated": "2025-09-04"
  },
  "AAPL": {
    "price": 239.78,
    "name": "Apple Inc.",
    "lastUpdated": "2025-09-04"
  },
  "MSFT": {
    "price": 507.97,
    "name": "Microsoft Corporation",
    "lastUpdated": "2025-09-04"
  },
  "NVDA": {
    "price": 171.66,
    "name": "NVIDIA Corporation",
    "lastUpdated": "2025-09-04"
  },
  "AMZN": {
    "price": 235.68,
    "name": "Amazon.com Inc.",
    "lastUpdated": "2025-09-04"
  },
  "META": {
    "price": 748.65,
    "name": "Meta Platforms Inc.",
    "lastUpdated": "2025-09-04"
  },
  "NFLX": {
    "price": 1257.48,
    "name": "Netflix Inc.",
    "lastUpdated": "2025-09-04"
  },
  "SPY": {
    "price": 649.12,
    "name": "SPDR S&P 500 ETF Trust",
    "lastUpdated": "2025-09-04"
  }
}